setup.py
cloak/__init__.py
cloak/immutable.py
cloak/monadic.py
cloak/option.py
cloak/try_type.py
cloak.egg-info/PKG-INFO
cloak.egg-info/SOURCES.txt
cloak.egg-info/dependency_links.txt
cloak.egg-info/top_level.txt