Metadata-Version: 1.1
Name: cloak
Version: 0.0.1a4
Summary: A library of container data structures
Home-page: https://bitbucket.org/rpcope1/cloak
Author: Robert Cope
Author-email: rpcope1@gmail.com
License: UNKNOWN
Platform: UNKNOWN
Classifier: Development Status :: 2 - Pre-Alpha
Classifier: Topic :: Software Development :: Libraries :: Python Modules
Classifier: License :: OSI Approved :: BSD License
